editdistancek_rs-1.0.0.dist-info/METADATA
editdistancek_rs-1.0.0.dist-info/WHEEL
editdistancek_rs-1.0.0.dist-info/licenses/LICENSE
editdistancek_rs/__init__.py
editdistancek_rs/py.typed
editdistancek_rs/__init__.pyi
editdistancek_rs/_native.abi3.so
editdistancek_rs-1.0.0.dist-info/RECORD
