Metadata-Version: 2.4
Name: editdistancek-rs
Version: 1.0.0
Classifier: Programming Language :: Rust
License-File: LICENSE
Summary: Algorithm for computing edit distance
Keywords: text,distance,edit
Author: Joshix, Nikolai Karpov
License: MIT
Requires-Python: >=3.12
Project-URL: Source Code, https://github.com/Joshix-1/editdistancek
